LICENSE
LICENSE_StyleGAN3
README.md
pyproject.toml
setup.py
firewood/__init__.py
firewood/__version__.py
firewood/common/__init__.py
firewood/common/backend.py
firewood/common/constant.py
firewood/common/types.py
firewood/csrc/extensions.cpp
firewood/csrc/biased_activations/biased_activations.cpp
firewood/csrc/biased_activations/biased_activations.h
firewood/csrc/biased_activations/biased_activations_kernel.cu
firewood/csrc/biased_activations/extension.h
firewood/csrc/upfirdn2d/extension.h
firewood/csrc/upfirdn2d/upfirdn2d.cpp
firewood/csrc/upfirdn2d/upfirdn2d.h
firewood/csrc/upfirdn2d/upfirdn2d_kernel.cu
firewood/layers/__init__.py
firewood/layers/activations.py
firewood/layers/bias.py
firewood/layers/biased_activations.py
firewood/layers/block.py
firewood/layers/clamp.py
firewood/layers/conv_blocks.py
firewood/layers/conv_gradfix.py
firewood/layers/conv_separable.py
firewood/layers/denormalizations.py
firewood/layers/initializers.py
firewood/layers/linear.py
firewood/layers/lr_equalizers.py
firewood/layers/noise.py
firewood/layers/normalizations.py
firewood/layers/reshape.py
firewood/layers/upfirdn.py
firewood/layers/weight_normalizations.py
firewood/models/__init__.py
firewood/models/gan/DCGAN.py
firewood/models/gan/GAN.py
firewood/models/gan/LSGAN.py
firewood/models/gan/__init__.py
firewood/models/gan/pix2pix.py
firewood/models/gan/pix2pixHD.py
firewood/models/semantic_segmentation/BiSeNetV1.py
firewood/models/semantic_segmentation/BiSeNetV2.py
firewood/models/semantic_segmentation/__init__.py
firewood/trainer/__init__.py
firewood/trainer/callbacks/__init__.py
firewood/trainer/callbacks/image.py
firewood/trainer/callbacks/image_generation.py
firewood/trainer/callbacks/model_checkpoint.py
firewood/trainer/callbacks/variational.py
firewood/trainer/gan/DCGAN.py
firewood/trainer/gan/GAN.py
firewood/trainer/gan/LSGAN.py
firewood/trainer/gan/__init__.py
firewood/trainer/gan/pix2pix.py
firewood/trainer/gan/pix2pixHD.py
firewood/trainer/losses/__init__.py
torch_firewood.egg-info/PKG-INFO
torch_firewood.egg-info/SOURCES.txt
torch_firewood.egg-info/dependency_links.txt
torch_firewood.egg-info/requires.txt
torch_firewood.egg-info/top_level.txt