Metadata-Version: 2.1
Name: torch-firewood
Version: 0.0.2
Summary: Firewood is a PyTorch implementation of layers and models.
Home-page: https://github.com/kynk94/torch-firewood
Author: firewood team
Author-email: kynk94@naver.com
License: MIT
Platform: UNKNOWN
Classifier: Programming Language :: Python :: 3
Classifier: Operating System :: OS Independent
Requires-Python: >=3.8
Provides-Extra: all
Provides-Extra: dev
License-File: LICENSE
License-File: LICENSE_StyleGAN3
